jupyter_deploy/__init__.py
jupyter_deploy/cmd_utils.py
jupyter_deploy/constants.py
jupyter_deploy/enum.py
jupyter_deploy/fs_utils.py
jupyter_deploy/manifest.py
jupyter_deploy/py.typed
jupyter_deploy/str_utils.py
jupyter_deploy/template_utils.py
jupyter_deploy/transform_utils.py
jupyter_deploy/type_utils.py
jupyter_deploy/variables_config.py
jupyter_deploy/verify_utils.py
jupyter_deploy/api/__init__.py
jupyter_deploy/api/aws/__init__.py
jupyter_deploy/api/aws/ec2/__init__.py
jupyter_deploy/api/aws/ec2/ec2_instance.py
jupyter_deploy/api/aws/ssm/__init__.py
jupyter_deploy/api/aws/ssm/ssm_command.py
jupyter_deploy/api/aws/ssm/ssm_session.py
jupyter_deploy/cli/app.py
jupyter_deploy/cli/host_app.py
jupyter_deploy/cli/organization_app.py
jupyter_deploy/cli/servers_app.py
jupyter_deploy/cli/teams_app.py
jupyter_deploy/cli/users_app.py
jupyter_deploy/cli/variables_decorator.py
jupyter_deploy/engine/__init__.py
jupyter_deploy/engine/engine_config.py
jupyter_deploy/engine/engine_down.py
jupyter_deploy/engine/engine_open.py
jupyter_deploy/engine/engine_outputs.py
jupyter_deploy/engine/engine_up.py
jupyter_deploy/engine/engine_variables.py
jupyter_deploy/engine/enum.py
jupyter_deploy/engine/outdefs.py
jupyter_deploy/engine/vardefs.py
jupyter_deploy/engine/terraform/tf_config.py
jupyter_deploy/engine/terraform/tf_constants.py
jupyter_deploy/engine/terraform/tf_down.py
jupyter_deploy/engine/terraform/tf_open.py
jupyter_deploy/engine/terraform/tf_outdefs.py
jupyter_deploy/engine/terraform/tf_outfiles.py
jupyter_deploy/engine/terraform/tf_outputs.py
jupyter_deploy/engine/terraform/tf_plan.py
jupyter_deploy/engine/terraform/tf_types.py
jupyter_deploy/engine/terraform/tf_up.py
jupyter_deploy/engine/terraform/tf_vardefs.py
jupyter_deploy/engine/terraform/tf_varfiles.py
jupyter_deploy/engine/terraform/tf_variables.py
jupyter_deploy/handlers/__init__.py
jupyter_deploy/handlers/base_project_handler.py
jupyter_deploy/handlers/init_handler.py
jupyter_deploy/handlers/access/__init__.py
jupyter_deploy-0.3.0.dist-info/METADATA
jupyter_deploy-0.3.0.dist-info/WHEEL
jupyter_deploy-0.3.0.dist-info/entry_points.txt
jupyter_deploy-0.3.0.dist-info/licenses/LICENSE
jupyter_deploy-0.3.0.dist-info/RECORD
