Metadata-Version: 2.4
Name: jupyter-deploy
Version: 0.3.0
Summary: CLI based tool to deploy Jupyter applications that integrates with infrastructure as code frameworks.
Project-URL: Homepage, https://github.com/jupyter-infra/jupyter-deploy
Project-URL: github, https://github.com/jupyter-infra/jupyter-deploy/tree/main/libs/jupyter-deploy
Author-email: Jonathan Guinegagne <jggg@amazon.com>, Michael Chin <chnmch@amazon.com>, Brian Granger <brgrange@amazon.com>
License: MIT License
License-File: LICENSE
Requires-Python: >=3.12
Requires-Dist: click<8.2.0
Requires-Dist: decorator>=5.2.1
Requires-Dist: jupyter-core>=5.0.0
Requires-Dist: jupyter-deploy-tf-aws-ec2-base
Requires-Dist: packaging>=25.0
Requires-Dist: pydantic>=2.11.5
Requires-Dist: python-hcl2>=7.2.1
Requires-Dist: pyyaml>=6.0.2
Requires-Dist: typer>=0.15.4
Requires-Dist: types-pyyaml>=6.0.12.20250516
Provides-Extra: aws
Requires-Dist: boto3-stubs>=1.38.23; extra == 'aws'
Requires-Dist: boto3>=1.38.23; extra == 'aws'
Requires-Dist: mypy-boto3-ec2>=1.40.4; extra == 'aws'
Requires-Dist: mypy-boto3-ssm>=1.38.5; extra == 'aws'
